[{"first_name": "Terry", "last_name": "Poole", "email": "aliciaroberts@example.net"}, {"first_name": "Brenda", "last_name": "Snyder", "email": "deandouglas@example.com"}, {"first_name": "Kara", "last_name": "Copeland", "email": "amanda95@example.net"}, {"first_name": "David", "last_name": "Hull", "email": "joshuaterry@example.org"}, {"first_name": "Mindy", "last_name": "Everett", "email": "edwardsrobert@example.com"}, {"first_name": "Heather", "last_name": "Watson", "email": "lisa89@example.org"}, {"first_name": "Darren", "last_name": "Johnson", "email": "madisonnichols@example.com"}, {"first_name": "Jack", "last_name": "Willis", "email": "tlee@example.com"}, {"first_name": "Miguel", "last_name": "Clark", "email": "parksmelissa@example.org"}, {"first_name": "Katrina", "last_name": "Dixon", "email": "melissa81@example.com"}, {"first_name": "Edward", "last_name": "Nixon", "email": "colin09@example.com"}, {"first_name": "Michelle", "last_name": "French", "email": "sandra09@example.org"}, {"first_name": "Matthew", "last_name": "Hayes", "email": "donna35@example.net"}, {"first_name": "David", "last_name": "Miller", "email": "archernathaniel@example.com"}, {"first_name": "Raven", "last_name": "Russo", "email": "nicholsalexander@example.net"}, {"first_name": "Gary", "last_name": "Davis", "email": "wendy25@example.net"}, {"first_name": "Tara", "last_name": "Wang", "email": "sanchezmary@example.net"}, {"first_name": "Sharon", "last_name": "Reyes", "email": "caseymurphy@example.org"}, {"first_name": "Jacob", "last_name": "Cobb", "email": "rebeccacollins@example.org"}, {"first_name": "Holly", "last_name": "Gonzalez", "email": "david84@example.net"}, {"first_name": "Jacob", "last_name": "Collins", "email": "harperjuan@example.com"}, {"first_name": "Danny", "last_name": "Palmer", "email": "bishoptimothy@example.com"}, {"first_name": "Jessica", "last_name": "Martin", "email": "maryfitzgerald@example.net"}, {"first_name": "Reginald", "last_name": "Solis", "email": "dmunoz@example.net"}, {"first_name": "Amanda", "last_name": "James", "email": "itaylor@example.com"}, {"first_name": "Michael", "last_name": "Rodriguez", "email": "lmiller@example.com"}, {"first_name": "Earl", "last_name": "Garner", "email": "zglenn@example.com"}, {"first_name": "Cody", "last_name": "Sweeney", "email": "jvelez@example.com"}, {"first_name": "Anthony", "last_name": "White", "email": "walter46@example.com"}, {"first_name": "Leslie", "last_name": "Cantu", "email": "torresmatthew@example.net"}, {"first_name": "Todd", "last_name": "Campbell", "email": "holmeskatherine@example.com"}, {"first_name": "Molly", "last_name": "Woods", "email": "anthony50@example.com"}, {"first_name": "Patricia", "last_name": "Martinez", "email": "xthompson@example.net"}, {"first_name": "Anna", "last_name": "Molina", "email": "nicholaspayne@example.net"}, {"first_name": "Robert", "last_name": "Vasquez", "email": "lperkins@example.com"}, {"first_name": "Debbie", "last_name": "Mcgrath", "email": "tom73@example.net"}, {"first_name": "Dwayne", "last_name": "Smith", "email": "kjones@example.net"}, {"first_name": "Kristy", "last_name": "Powers", "email": "bianca79@example.com"}, {"first_name": "Jon", "last_name": "Barron", "email": "lramirez@example.com"}, {"first_name": "Chad", "last_name": "Watkins", "email": "moorekelli@example.org"}, {"first_name": "Richard", "last_name": "Campos", "email": "harpertiffany@example.net"}, {"first_name": "Michael", "last_name": "Gonzalez", "email": "ashleyhall@example.org"}, {"first_name": "Wendy", "last_name": "Aguilar", "email": "omar43@example.net"}, {"first_name": "Karen", "last_name": "Combs", "email": "rjones@example.org"}, {"first_name": "Samuel", "last_name": "Wilson", "email": "manuelmartin@example.com"}, {"first_name": "Carolyn", "last_name": "Oneal", "email": "david29@example.com"}, {"first_name": "Ashley", "last_name": "House", "email": "kmartin@example.net"}, {"first_name": "Lori", "last_name": "Young", "email": "brownmichael@example.com"}, {"first_name": "Jessica", "last_name": "Herrera", "email": "kevin47@example.com"}, {"first_name": "John", "last_name": "Gross", "email": "crystal51@example.org"}, {"first_name": "Leon", "last_name": "Smith", "email": "samanthasmith@example.com"}, {"first_name": "Katelyn", "last_name": "Smith", "email": "frysandra@example.com"}, {"first_name": "Aaron", "last_name": "Turner", "email": "tylerjefferson@example.com"}, {"first_name": "Ryan", "last_name": "Carter", "email": "richardmartin@example.net"}, {"first_name": "Justin", "last_name": "Adams", "email": "lauraali@example.org"}, {"first_name": "Jenna", "last_name": "Bishop", "email": "robinsmith@example.com"}, {"first_name": "Whitney", "last_name": "Wood", "email": "brandonwalter@example.com"}, {"first_name": "Morgan", "last_name": "Brown", "email": "mark65@example.com"}, {"first_name": "Bruce", "last_name": "Thompson", "email": "jaimedavenport@example.net"}, {"first_name": "Jacob", "last_name": "Miller", "email": "joseph80@example.com"}, {"first_name": "Gerald", "last_name": "Cole", "email": "lrodriguez@example.org"}, {"first_name": "Heather", "last_name": "Hunter", "email": "phelpsjulie@example.net"}, {"first_name": "Patricia", "last_name": "Saunders", "email": "tstewart@example.org"}, {"first_name": "Amanda", "last_name": "Hale", "email": "ocaldwell@example.com"}, {"first_name": "Scott", "last_name": "Montgomery", "email": "ashields@example.net"}, {"first_name": "Michael", "last_name": "Gonzalez", "email": "robertsangela@example.net"}, {"first_name": "Katherine", "last_name": "Holloway", "email": "gentrychris@example.net"}, {"first_name": "Tabitha", "last_name": "Luna", "email": "donald70@example.com"}, {"first_name": "Timothy", "last_name": "Mcclain", "email": "wbauer@example.org"}, {"first_name": "Bonnie", "last_name": "Dennis", "email": "lconner@example.org"}, {"first_name": "Linda", "last_name": "Stone", "email": "jeff53@example.com"}, {"first_name": "Edwin", "last_name": "Glass", "email": "wchristensen@example.org"}, {"first_name": "Ricky", "last_name": "Fleming", "email": "reevesjesse@example.net"}, {"first_name": "Donna", "last_name": "Carter", "email": "kari41@example.org"}, {"first_name": "Ashley", "last_name": "Fowler", "email": "john20@example.net"}, {"first_name": "Michael", "last_name": "Ross", "email": "roberto78@example.org"}, {"first_name": "Madeline", "last_name": "Carr", "email": "dsalazar@example.org"}, {"first_name": "Scott", "last_name": "Patterson", "email": "rterrell@example.org"}, {"first_name": "Samuel", "last_name": "Lara", "email": "douglashubbard@example.net"}, {"first_name": "Justin", "last_name": "Rodriguez", "email": "april42@example.org"}, {"first_name": "Ryan", "last_name": "Spencer", "email": "mollywilliams@example.net"}, {"first_name": "Amanda", "last_name": "Rangel", "email": "ryananderson@example.net"}, {"first_name": "Bailey", "last_name": "Harrison", "email": "haydenjoseph@example.net"}, {"first_name": "Denise", "last_name": "Miller", "email": "clarkpatricia@example.net"}, {"first_name": "Bradley", "last_name": "Holt", "email": "clarknicholas@example.org"}, {"first_name": "Jill", "last_name": "Gentry", "email": "mannjudy@example.net"}, {"first_name": "Billy", "last_name": "Garcia", "email": "scottallen@example.com"}, {"first_name": "Teresa", "last_name": "Martin", "email": "williamsmelvin@example.net"}, {"first_name": "Krystal", "last_name": "Diaz", "email": "richard73@example.net"}, {"first_name": "Jennifer", "last_name": "Barnett", "email": "garciamichael@example.org"}, {"first_name": "Kristy", "last_name": "Garcia", "email": "ortizryan@example.net"}, {"first_name": "Martha", "last_name": "Tran", "email": "fergusonjennifer@example.net"}, {"first_name": "Michael", "last_name": "Cobb", "email": "bakermichelle@example.net"}, {"first_name": "Victoria", "last_name": "Medina", "email": "tammyharris@example.com"}, {"first_name": "Adam", "last_name": "Jones", "email": "martin19@example.com"}, {"first_name": "Kim", "last_name": "Duncan", "email": "marcusward@example.com"}, {"first_name": "James", "last_name": "Smith", "email": "wernereric@example.net"}, {"first_name": "Tina", "last_name": "Quinn", "email": "jacobsmith@example.org"}, {"first_name": "Lori", "last_name": "Hill", "email": "hhoward@example.org"}, {"first_name": "Lisa", "last_name": "Garner", "email": "danielle42@example.net"}]